{
   "data":[
      {
         "cat":2493,
         "colors":[
            0,
            1,
            25,
            50
         ],
         "displayName":"Threat",
         "id":25072,
         "learnedat":1,
         "level":0,
         "name":"Threat",
         "nskillup":1,
         "reagents":[
            [
               22448,
               4
            ],
            [
               22446,
               2
            ],
            [
               21886,
               8
            ]
         ],
         "schools":1,
         "skill":[
            333
         ],
         "source":[
            2,
            5
         ]
      },
      {
         "cat":2493,
         "colors":[
            0,
            1,
            25,
            50
         ],
         "displayName":"Superior Agility",
         "id":25080,
         "learnedat":1,
         "level":0,
         "name":"Superior Agility",
         "nskillup":1,
         "reagents":[
            [
               22448,
               3
            ],
            [
               22446,
               3
            ],
            [
               22451,
               2
            ]
         ],
         "schools":1,
         "skill":[
            333
         ],
         "source":[
            2,
            5
         ]
      },
      {
         "cat":2493,
         "colors":[
            0,
            1,
            25,
            50
         ],
         "displayName":"Stealth",
         "id":25083,
         "learnedat":1,
         "level":0,
         "name":"Stealth",
         "nskillup":1,
         "reagents":[
            [
               22448,
               3
            ],
            [
               22446,
               3
            ],
            [
               22794,
               2
            ]
         ],
         "schools":1,
         "skill":[
            333
         ],
         "source":[
            2,
            5
         ]
      },
      {
         "cat":2493,
         "colors":[
            0,
            1,
            25,
            50
         ],
         "displayName":"Subtlety",
         "id":25084,
         "learnedat":1,
         "level":0,
         "name":"Subtlety",
         "nskillup":1,
         "reagents":[
            [
               22448,
               4
            ],
            [
               22446,
               2
            ],
            [
               22456,
               8
            ]
         ],
         "schools":1,
         "skill":[
            333
         ],
         "source":[
            2,
            5
         ]
      },
      {
         "cat":2493,
         "colors":[
            0,
            1,
            25,
            50
         ],
         "displayName":"Dodge",
         "id":25086,
         "learnedat":1,
         "level":0,
         "name":"Dodge",
         "nskillup":1,
         "reagents":[
            [
               22448,
               3
            ],
            [
               22446,
               3
            ],
            [
               22452,
               8
            ]
         ],
         "schools":1,
         "skill":[
            333
         ],
         "source":[
            2,
            5
         ]
      },
      {
         "cat":2493,
         "colors":[
            0,
            0,
            0,
            305
         ],
         "displayName":"Brawn",
         "id":27899,
         "learnedat":305,
         "level":0,
         "name":"Brawn",
         "nskillup":1,
         "reagents":[
            [
               22445,
               6
            ]
         ],
         "schools":1,
         "skill":[
            333
         ],
         "trainingcost":12500
      },
      {
         "cat":2493,
         "colors":[
            0,
            0,
            0,
            315
         ],
         "displayName":"Stats",
         "id":27905,
         "learnedat":315,
         "level":0,
         "name":"Stats",
         "nskillup":1,
         "reagents":[
            [
               22445,
               6
            ],
            [
               22447,
               6
            ]
         ],
         "schools":1,
         "skill":[
            333
         ],
         "trainingcost":12500
      },
      {
         "cat":2493,
         "colors":[
            0,
            30,
            45,
            60
         ],
         "displayName":"Greater Dodge",
         "id":27906,
         "learnedat":30,
         "level":0,
         "name":"Greater Dodge",
         "nskillup":1,
         "reagents":[
            [
               22448,
               2
            ],
            [
               22445,
               10
            ]
         ],
         "schools":1,
         "skill":[
            333
         ],
         "source":[
            2
         ]
      },
      {
         "cat":2493,
         "colors":[
            0,
            35,
            50,
            65
         ],
         "displayName":"Superior Healing",
         "id":27911,
         "learnedat":35,
         "level":0,
         "name":"Superior Healing",
         "nskillup":1,
         "reagents":[
            [
               22446,
               4
            ],
            [
               21886,
               4
            ]
         ],
         "schools":1,
         "skill":[
            333
         ],
         "source":[
            5
         ]
      },
      {
         "cat":2493,
         "colors":[
            0,
            45,
            55,
            65
         ],
         "displayName":"Versatility Prime",
         "id":27913,
         "learnedat":45,
         "level":0,
         "name":"Versatility Prime",
         "nskillup":1,
         "reagents":[
            [
               22446,
               8
            ]
         ],
         "schools":1,
         "skill":[
            333
         ],
         "source":[
            2
         ]
      },
      {
         "cat":2493,
         "colors":[
            0,
            70,
            72,
            75
         ],
         "displayName":"Fortitude",
         "id":27914,
         "learnedat":70,
         "level":0,
         "name":"Fortitude",
         "nskillup":1,
         "reagents":[
            [
               22449,
               1
            ],
            [
               22446,
               10
            ],
            [
               22445,
               20
            ]
         ],
         "schools":1,
         "skill":[
            333
         ],
         "source":[
            2
         ]
      },
      {
         "cat":2493,
         "colors":[
            0,
            70,
            72,
            75
         ],
         "displayName":"Spellpower",
         "id":27917,
         "learnedat":70,
         "level":0,
         "name":"Spellpower",
         "nskillup":1,
         "reagents":[
            [
               22449,
               6
            ],
            [
               21884,
               6
            ],
            [
               21885,
               6
            ]
         ],
         "schools":1,
         "skill":[
            333
         ],
         "source":[
            2
         ]
      },
      {
         "cat":2493,
         "colors":[
            0,
            0,
            0,
            310
         ],
         "displayName":"Lesser Dodge",
         "id":27944,
         "learnedat":310,
         "level":0,
         "name":"Lesser Dodge",
         "nskillup":1,
         "reagents":[
            [
               22445,
               6
            ],
            [
               22452,
               10
            ]
         ],
         "schools":1,
         "skill":[
            333
         ],
         "trainingcost":15000
      },
      {
         "cat":2493,
         "colors":[
            0,
            35,
            50,
            65
         ],
         "displayName":"Intellect",
         "id":27945,
         "learnedat":35,
         "level":0,
         "name":"Intellect",
         "nskillup":1,
         "reagents":[
            [
               22446,
               4
            ]
         ],
         "schools":1,
         "skill":[
            333
         ],
         "source":[
            5
         ]
      },
      {
         "cat":2493,
         "colors":[
            0,
            50,
            62,
            75
         ],
         "displayName":"Parry",
         "id":27946,
         "learnedat":50,
         "level":0,
         "name":"Parry",
         "nskillup":1,
         "reagents":[
            [
               22445,
               12
            ],
            [
               22446,
               4
            ],
            [
               22452,
               10
            ]
         ],
         "schools":1,
         "skill":[
            333
         ],
         "source":[
            2
         ]
      },
      {
         "cat":2493,
         "colors":[
            0,
            15,
            30,
            45
         ],
         "displayName":"Vitality",
         "id":27948,
         "learnedat":15,
         "level":0,
         "name":"Vitality",
         "nskillup":1,
         "reagents":[
            [
               22445,
               6
            ],
            [
               13446,
               4
            ],
            [
               13444,
               4
            ]
         ],
         "schools":1,
         "skill":[
            333
         ],
         "source":[
            2
         ]
      },
      {
         "cat":2493,
         "colors":[
            0,
            30,
            45,
            60
         ],
         "displayName":"Fortitude",
         "id":27950,
         "learnedat":30,
         "level":0,
         "name":"Fortitude",
         "nskillup":1,
         "reagents":[
            [
               22445,
               12
            ]
         ],
         "schools":1,
         "skill":[
            333
         ],
         "source":[
            2
         ]
      },
      {
         "cat":2493,
         "colors":[
            0,
            50,
            62,
            75
         ],
         "displayName":"Dexterity",
         "id":27951,
         "learnedat":50,
         "level":0,
         "name":"Dexterity",
         "nskillup":1,
         "reagents":[
            [
               22446,
               8
            ],
            [
               22445,
               8
            ]
         ],
         "schools":1,
         "skill":[
            333
         ],
         "source":[
            2
         ]
      },
      {
         "cat":2493,
         "colors":[
            0,
            75,
            75,
            75
         ],
         "displayName":"Surefooted",
         "id":27954,
         "learnedat":75,
         "level":0,
         "name":"Surefooted",
         "nskillup":1,
         "reagents":[
            [
               22450,
               2
            ],
            [
               22449,
               4
            ]
         ],
         "schools":1,
         "skill":[
            333
         ],
         "source":[
            2
         ]
      },
      {
         "cat":2493,
         "colors":[
            0,
            0,
            0,
            315
         ],
         "displayName":"Exceptional Health",
         "id":27957,
         "learnedat":315,
         "level":0,
         "name":"Exceptional Health",
         "nskillup":1,
         "reagents":[
            [
               22445,
               10
            ],
            [
               13446,
               6
            ]
         ],
         "schools":1,
         "skill":[
            333
         ],
         "trainingcost":17500
      },
      {
         "cat":2493,
         "colors":[
            0,
            55,
            65,
            75
         ],
         "displayName":"Exceptional Stats",
         "id":27960,
         "learnedat":55,
         "level":0,
         "name":"Exceptional Stats",
         "nskillup":1,
         "reagents":[
            [
               22449,
               4
            ],
            [
               22445,
               4
            ],
            [
               22446,
               4
            ]
         ],
         "schools":1,
         "skill":[
            333
         ],
         "source":[
            5
         ]
      },
      {
         "cat":2493,
         "colors":[
            0,
            0,
            0,
            310
         ],
         "displayName":"Major Armor",
         "id":27961,
         "learnedat":310,
         "level":0,
         "name":"Major Armor",
         "nskillup":1,
         "reagents":[
            [
               22445,
               8
            ]
         ],
         "schools":1,
         "skill":[
            333
         ],
         "trainingcost":15000
      },
      {
         "cat":2493,
         "colors":[
            0,
            50,
            62,
            75
         ],
         "displayName":"Major Striking",
         "id":27967,
         "learnedat":50,
         "level":0,
         "name":"Major Striking",
         "nskillup":1,
         "reagents":[
            [
               22449,
               2
            ],
            [
               22446,
               6
            ],
            [
               22445,
               6
            ]
         ],
         "schools":1,
         "skill":[
            333
         ],
         "source":[
            5
         ]
      },
      {
         "cat":2493,
         "colors":[
            0,
            50,
            62,
            75
         ],
         "displayName":"Major Intellect",
         "id":27968,
         "learnedat":50,
         "level":0,
         "name":"Major Intellect",
         "nskillup":1,
         "reagents":[
            [
               22449,
               2
            ],
            [
               22446,
               10
            ]
         ],
         "schools":1,
         "skill":[
            333
         ],
         "source":[
            2
         ]
      },
      {
         "cat":2493,
         "colors":[
            0,
            70,
            72,
            75
         ],
         "displayName":"Potency",
         "id":27972,
         "learnedat":70,
         "level":0,
         "name":"Potency",
         "nskillup":1,
         "reagents":[
            [
               22449,
               4
            ],
            [
               22446,
               5
            ],
            [
               22445,
               20
            ]
         ],
         "schools":1,
         "skill":[
            333
         ],
         "source":[
            2
         ]
      },
      {
         "cat":2493,
         "colors":[
            0,
            70,
            72,
            75
         ],
         "displayName":"Savagery",
         "id":27971,
         "learnedat":70,
         "level":0,
         "name":"Savagery",
         "nskillup":1,
         "reagents":[
            [
               22449,
               4
            ],
            [
               22445,
               40
            ]
         ],
         "schools":1,
         "skill":[
            333
         ],
         "source":[
            2
         ]
      },
      {
         "cat":2493,
         "colors":[
            0,
            70,
            72,
            75
         ],
         "displayName":"Major Spellpower",
         "id":27975,
         "learnedat":70,
         "level":0,
         "name":"Major Spellpower",
         "nskillup":1,
         "reagents":[
            [
               22449,
               8
            ],
            [
               22446,
               8
            ]
         ],
         "schools":1,
         "skill":[
            333
         ],
         "source":[
            2
         ]
      },
      {
         "cat":2493,
         "colors":[
            0,
            70,
            72,
            75
         ],
         "displayName":"Major Agility",
         "id":27977,
         "learnedat":70,
         "level":0,
         "name":"Major Agility",
         "nskillup":1,
         "reagents":[
            [
               22449,
               8
            ],
            [
               22446,
               6
            ],
            [
               22445,
               20
            ]
         ],
         "schools":1,
         "skill":[
            333
         ],
         "source":[
            2
         ]
      },
      {
         "cat":2493,
         "colors":[
            0,
            70,
            72,
            75
         ],
         "displayName":"Battlemaster",
         "id":28004,
         "learnedat":70,
         "level":0,
         "name":"Battlemaster",
         "nskillup":1,
         "reagents":[
            [
               22450,
               8
            ],
            [
               22449,
               8
            ],
            [
               21885,
               2
            ]
         ],
         "schools":1,
         "skill":[
            333
         ],
         "source":[
            2
         ]
      },
      {
         "cat":2493,
         "colors":[
            0,
            70,
            72,
            75
         ],
         "displayName":"Spellsurge",
         "id":28003,
         "learnedat":70,
         "level":0,
         "name":"Spellsurge",
         "nskillup":1,
         "reagents":[
            [
               22449,
               12
            ],
            [
               22446,
               10
            ],
            [
               22445,
               20
            ]
         ],
         "schools":1,
         "skill":[
            333
         ],
         "source":[
            2
         ]
      },
      {
         "cat":2493,
         "colors":[
            0,
            75,
            75,
            75
         ],
         "displayName":"Mongoose",
         "id":27984,
         "learnedat":75,
         "level":0,
         "name":"Mongoose",
         "nskillup":1,
         "reagents":[
            [
               22450,
               6
            ],
            [
               22449,
               10
            ],
            [
               22446,
               8
            ],
            [
               22445,
               40
            ]
         ],
         "schools":1,
         "skill":[
            333
         ],
         "source":[
            2
         ]
      },
      {
         "cat":2493,
         "colors":[
            0,
            75,
            75,
            75
         ],
         "displayName":"Sunfire",
         "id":27981,
         "learnedat":75,
         "level":0,
         "name":"Sunfire",
         "nskillup":1,
         "reagents":[
            [
               22450,
               12
            ],
            [
               22449,
               10
            ],
            [
               22446,
               8
            ],
            [
               21884,
               6
            ],
            [
               23571,
               1
            ]
         ],
         "schools":1,
         "skill":[
            333
         ],
         "source":[
            2
         ]
      },
      {
         "cat":2493,
         "colors":[
            0,
            75,
            75,
            75
         ],
         "displayName":"Soulfrost",
         "id":27982,
         "learnedat":75,
         "level":0,
         "name":"Soulfrost",
         "nskillup":1,
         "reagents":[
            [
               22450,
               12
            ],
            [
               22449,
               10
            ],
            [
               22446,
               8
            ],
            [
               21885,
               6
            ],
            [
               22456,
               6
            ]
         ],
         "schools":1,
         "skill":[
            333
         ],
         "source":[
            2
         ]
      },
      {
         "cat":2493,
         "colors":[
            0,
            10,
            20,
            30
         ],
         "creates":[
            22521,
            1,
            1
         ],
         "displayName":"Superior Mana Oil",
         "id":28016,
         "learnedat":10,
         "level":0,
         "name":"Superior Mana Oil",
         "nskillup":1,
         "quality":1,
         "reagents":[
            [
               22445,
               3
            ],
            [
               22791,
               1
            ],
            [
               3371,
               1
            ]
         ],
         "schools":1,
         "skill":[
            333
         ],
         "source":[
            5
         ]
      },
      {
         "cat":2493,
         "colors":[
            0,
            40,
            50,
            60
         ],
         "creates":[
            22522,
            1,
            1
         ],
         "displayName":"Superior Wizard Oil",
         "id":28019,
         "learnedat":40,
         "level":0,
         "name":"Superior Wizard Oil",
         "nskillup":1,
         "quality":1,
         "reagents":[
            [
               22445,
               3
            ],
            [
               22792,
               1
            ],
            [
               3371,
               1
            ]
         ],
         "schools":1,
         "skill":[
            333
         ],
         "source":[
            5
         ]
      },
      {
         "cat":2493,
         "colors":[
            0,
            1,
            3,
            5
         ],
         "creates":[
            22449,
            1,
            1
         ],
         "displayName":"Large Prismatic Shard",
         "id":28022,
         "learnedat":1,
         "level":0,
         "name":"Large Prismatic Shard",
         "nskillup":1,
         "quality":3,
         "reagents":[
            [
               22448,
               3
            ]
         ],
         "schools":1,
         "skill":[
            333
         ],
         "source":[
            5
         ]
      },
      {
         "cat":2493,
         "colors":[
            0,
            0,
            0,
            320
         ],
         "displayName":"Major Versatility",
         "id":33990,
         "learnedat":320,
         "level":0,
         "name":"Major Versatility",
         "nskillup":1,
         "reagents":[
            [
               22446,
               2
            ]
         ],
         "schools":1,
         "skill":[
            333
         ],
         "trainingcost":20000
      },
      {
         "cat":2493,
         "colors":[
            0,
            0,
            0,
            300
         ],
         "displayName":"Versatility Prime",
         "id":33991,
         "learnedat":300,
         "level":0,
         "name":"Versatility Prime",
         "nskillup":1,
         "reagents":[
            [
               22447,
               2
            ],
            [
               22445,
               2
            ]
         ],
         "schools":1,
         "skill":[
            333
         ],
         "trainingcost":20000
      },
      {
         "cat":2493,
         "colors":[
            0,
            55,
            65,
            75
         ],
         "displayName":"Major Armor",
         "id":33992,
         "learnedat":55,
         "level":0,
         "name":"Major Armor",
         "nskillup":1,
         "reagents":[
            [
               22446,
               4
            ],
            [
               22445,
               10
            ]
         ],
         "schools":1,
         "skill":[
            333
         ],
         "source":[
            2
         ]
      },
      {
         "cat":2493,
         "colors":[
            0,
            0,
            0,
            305
         ],
         "displayName":"Blasting",
         "id":33993,
         "learnedat":305,
         "level":0,
         "name":"Blasting",
         "nskillup":1,
         "reagents":[
            [
               22447,
               1
            ],
            [
               22445,
               4
            ]
         ],
         "schools":1,
         "skill":[
            333
         ],
         "trainingcost":12500
      },
      {
         "cat":2493,
         "colors":[
            0,
            70,
            72,
            75
         ],
         "displayName":"Precise Strikes",
         "id":33994,
         "learnedat":70,
         "level":0,
         "name":"Precise Strikes",
         "nskillup":1,
         "reagents":[
            [
               22446,
               8
            ],
            [
               22445,
               2
            ],
            [
               22449,
               2
            ]
         ],
         "schools":1,
         "skill":[
            333
         ],
         "source":[
            5
         ]
      },
      {
         "cat":2493,
         "colors":[
            0,
            0,
            0,
            340
         ],
         "displayName":"Major Strength",
         "id":33995,
         "learnedat":340,
         "level":0,
         "name":"Major Strength",
         "nskillup":1,
         "reagents":[
            [
               22445,
               12
            ],
            [
               22446,
               1
            ]
         ],
         "schools":1,
         "skill":[
            333
         ],
         "trainingcost":25000
      },
      {
         "cat":2493,
         "colors":[
            0,
            0,
            0,
            310
         ],
         "displayName":"Assault",
         "id":33996,
         "learnedat":310,
         "level":0,
         "name":"Assault",
         "nskillup":1,
         "reagents":[
            [
               22445,
               8
            ]
         ],
         "schools":1,
         "skill":[
            333
         ],
         "trainingcost":15000
      },
      {
         "cat":2493,
         "colors":[
            0,
            70,
            72,
            75
         ],
         "displayName":"Major Spellpower",
         "id":33997,
         "learnedat":70,
         "level":0,
         "name":"Major Spellpower",
         "nskillup":1,
         "reagents":[
            [
               22446,
               6
            ],
            [
               22449,
               6
            ],
            [
               22457,
               6
            ]
         ],
         "schools":1,
         "skill":[
            333
         ],
         "source":[
            5
         ]
      },
      {
         "cat":2493,
         "colors":[
            0,
            70,
            72,
            75
         ],
         "displayName":"Major Healing",
         "id":33999,
         "learnedat":70,
         "level":0,
         "name":"Major Healing",
         "nskillup":1,
         "reagents":[
            [
               22446,
               6
            ],
            [
               22449,
               6
            ],
            [
               21886,
               6
            ]
         ],
         "schools":1,
         "skill":[
            333
         ],
         "source":[
            5
         ]
      },
      {
         "cat":2493,
         "colors":[
            0,
            0,
            0,
            305
         ],
         "displayName":"Major Intellect",
         "id":34001,
         "learnedat":305,
         "level":0,
         "name":"Major Intellect",
         "nskillup":1,
         "reagents":[
            [
               22447,
               3
            ]
         ],
         "schools":1,
         "skill":[
            333
         ],
         "trainingcost":12500
      },
      {
         "cat":2493,
         "colors":[
            0,
            0,
            0,
            300
         ],
         "displayName":"Lesser Assault",
         "id":34002,
         "learnedat":300,
         "level":0,
         "name":"Lesser Assault",
         "nskillup":1,
         "reagents":[
            [
               22445,
               6
            ]
         ],
         "schools":1,
         "skill":[
            333
         ],
         "trainingcost":12500
      },
      {
         "cat":2493,
         "colors":[
            0,
            35,
            50,
            65
         ],
         "displayName":"PvP Power",
         "id":34003,
         "learnedat":35,
         "level":0,
         "name":"PvP Power",
         "nskillup":1,
         "reagents":[
            [
               22446,
               2
            ],
            [
               22445,
               6
            ],
            [
               22457,
               2
            ]
         ],
         "schools":1,
         "skill":[
            333
         ],
         "source":[
            5
         ]
      },
      {
         "cat":2493,
         "colors":[
            0,
            0,
            0,
            310
         ],
         "displayName":"Greater Agility",
         "id":34004,
         "learnedat":310,
         "level":0,
         "name":"Greater Agility",
         "nskillup":1,
         "reagents":[
            [
               22446,
               1
            ],
            [
               22445,
               4
            ],
            [
               22451,
               1
            ]
         ],
         "schools":1,
         "skill":[
            333
         ],
         "trainingcost":15000
      },
      {
         "cat":2493,
         "colors":[
            0,
            70,
            72,
            75
         ],
         "displayName":"Cat's Swiftness",
         "id":34007,
         "learnedat":70,
         "level":0,
         "name":"Cat's Swiftness",
         "nskillup":1,
         "reagents":[
            [
               22449,
               8
            ],
            [
               22451,
               8
            ]
         ],
         "schools":1,
         "skill":[
            333
         ],
         "source":[
            2
         ]
      },
      {
         "cat":2493,
         "colors":[
            0,
            70,
            72,
            75
         ],
         "displayName":"Boar's Speed",
         "id":34008,
         "learnedat":70,
         "level":0,
         "name":"Boar's Speed",
         "nskillup":1,
         "reagents":[
            [
               22449,
               8
            ],
            [
               22452,
               8
            ]
         ],
         "schools":1,
         "skill":[
            333
         ],
         "source":[
            2
         ]
      },
      {
         "cat":2493,
         "colors":[
            0,
            35,
            50,
            65
         ],
         "displayName":"Major Stamina",
         "id":34009,
         "learnedat":35,
         "level":0,
         "name":"Major Stamina",
         "nskillup":1,
         "reagents":[
            [
               22445,
               15
            ]
         ],
         "schools":1,
         "skill":[
            333
         ],
         "source":[
            5
         ]
      },
      {
         "cat":2493,
         "colors":[
            0,
            70,
            72,
            75
         ],
         "displayName":"Major Healing",
         "id":34010,
         "learnedat":70,
         "level":0,
         "name":"Major Healing",
         "nskillup":1,
         "reagents":[
            [
               22449,
               8
            ],
            [
               21885,
               8
            ],
            [
               21886,
               8
            ]
         ],
         "schools":1,
         "skill":[
            333
         ],
         "source":[
            5
         ]
      },
      {
         "cat":2493,
         "colors":[
            0,
            0,
            0,
            325
         ],
         "creates":[
            22460,
            1,
            1
         ],
         "displayName":"Prismatic Sphere",
         "id":28027,
         "learnedat":325,
         "level":0,
         "name":"Prismatic Sphere",
         "nskillup":1,
         "quality":3,
         "reagents":[
            [
               22449,
               4
            ]
         ],
         "schools":1,
         "skill":[
            333
         ],
         "trainingcost":40000
      },
      {
         "cat":2493,
         "colors":[
            0,
            0,
            0,
            350
         ],
         "creates":[
            22459,
            1,
            1
         ],
         "displayName":"Void Sphere",
         "id":28028,
         "learnedat":350,
         "level":0,
         "name":"Void Sphere",
         "nskillup":1,
         "quality":4,
         "reagents":[
            [
               22450,
               2
            ]
         ],
         "schools":1,
         "skill":[
            333
         ],
         "trainingcost":80000
      },
      {
         "cat":2493,
         "colors":[
            0,
            0,
            0,
            335
         ],
         "creates":[
            22448,
            3,
            3
         ],
         "displayName":"Small Prismatic Shard",
         "id":42615,
         "learnedat":335,
         "level":0,
         "name":"Small Prismatic Shard",
         "nskillup":1,
         "quality":3,
         "reagents":[
            [
               22449,
               1
            ]
         ],
         "schools":1,
         "skill":[
            333
         ],
         "trainingcost":40000
      },
      {
         "cat":2493,
         "colors":[
            0,
            60,
            67,
            75
         ],
         "displayName":"Greater Agility",
         "id":42620,
         "learnedat":60,
         "level":0,
         "name":"Greater Agility",
         "nskillup":1,
         "reagents":[
            [
               22445,
               8
            ],
            [
               22446,
               4
            ],
            [
               22449,
               6
            ],
            [
               22451,
               2
            ]
         ],
         "schools":1,
         "skill":[
            333
         ],
         "source":[
            5
         ]
      },
      {
         "cat":2493,
         "colors":[
            0,
            0,
            0,
            375
         ],
         "displayName":"Executioner",
         "id":42974,
         "learnedat":375,
         "level":0,
         "name":"Executioner",
         "nskillup":1,
         "reagents":[
            [
               22450,
               6
            ],
            [
               22449,
               10
            ],
            [
               22446,
               6
            ],
            [
               22445,
               30
            ],
            [
               22824,
               3
            ]
         ],
         "scaling":4877,
         "schools":1,
         "skill":[
            333
         ],
         "source":[
            5
         ]
      },
      {
         "cat":2493,
         "colors":[
            0,
            0,
            0,
            330
         ],
         "displayName":"Armor",
         "id":44383,
         "learnedat":330,
         "level":0,
         "name":"Armor",
         "nskillup":1,
         "reagents":[
            [
               22449,
               1
            ],
            [
               22447,
               4
            ]
         ],
         "schools":1,
         "skill":[
            333
         ],
         "trainingcost":25000
      },
      {
         "cat":2493,
         "colors":[
            0,
            60,
            62,
            65
         ],
         "creates":[
            22449,
            2,
            2
         ],
         "displayName":"Void Shatter",
         "id":45765,
         "learnedat":60,
         "level":0,
         "name":"Void Shatter",
         "nskillup":1,
         "quality":3,
         "reagents":[
            [
               22450,
               1
            ]
         ],
         "schools":1,
         "skill":[
            333
         ],
         "source":[
            5
         ]
      },
      {
         "cat":2493,
         "colors":[
            0,
            50,
            57,
            65
         ],
         "displayName":"Deathfrost",
         "id":46578,
         "learnedat":50,
         "level":0,
         "name":"Deathfrost",
         "nskillup":1,
         "reagents":[
            [
               22456,
               2
            ],
            [
               21885,
               2
            ]
         ],
         "schools":1,
         "skill":[
            333
         ],
         "source":[
            2
         ]
      },
      {
         "cat":2493,
         "colors":[
            0,
            70,
            72,
            75
         ],
         "displayName":"Dodge",
         "id":46594,
         "learnedat":70,
         "level":0,
         "name":"Dodge",
         "nskillup":1,
         "reagents":[
            [
               22446,
               4
            ],
            [
               22445,
               8
            ],
            [
               23427,
               4
            ]
         ],
         "schools":1,
         "skill":[
            333
         ],
         "source":[
            5
         ]
      },
      {
         "cat":2493,
         "colors":[
            0,
            75,
            75,
            75
         ],
         "displayName":"Greater Dodge",
         "id":47051,
         "learnedat":75,
         "level":0,
         "name":"Greater Dodge",
         "nskillup":1,
         "reagents":[
            [
               22446,
               8
            ],
            [
               22452,
               8
            ]
         ],
         "schools":1,
         "skill":[
            333
         ],
         "source":[
            2
         ]
      },
      {
         "cat":2493,
         "colors":[
            0,
            0,
            0,
            350
         ],
         "creates":[
            138789,
            1,
            1
         ],
         "displayName":"Tome of Illusions: Outland",
         "id":217641,
         "learnedat":350,
         "level":0,
         "name":"Tome of Illusions: Outland",
         "nskillup":1,
         "quality":3,
         "reagents":[
            [
               22450,
               10
            ],
            [
               22449,
               5
            ],
            [
               21884,
               5
            ],
            [
               22457,
               5
            ],
            [
               39354,
               3
            ]
         ],
         "schools":1,
         "skill":[
            333
         ],
         "trainingcost":80000
      }
   ]
}
