{
   "data":[
      {
         "cat":2878,
         "colors":[
            0,
            80,
            90,
            100
         ],
         "creates":[
            222552,
            1,
            1
         ],
         "displayName":"Algari Treatise on Herbalism",
         "id":444182,
         "learnedat":80,
         "level":0,
         "name":"Algari Treatise on Herbalism",
         "nskillup":1,
         "quality":3,
         "reagents":[
            [
               213612,
               2
            ],
            [
               222558,
               1
            ],
            [
               222615,
               2
            ]
         ],
         "schools":1,
         "skill":[
            773
         ],
         "optionalReagents":[
            {
               "id":323,
               "description":"Apricate Ink"
            },
            {
               "id":320,
               "description":"Boundless Cipher"
            }
         ]
      },
      {
         "cat":2878,
         "colors":[
            0,
            80,
            90,
            100
         ],
         "creates":[
            222553,
            1,
            1
         ],
         "displayName":"Algari Treatise on Mining",
         "id":444183,
         "learnedat":80,
         "level":0,
         "name":"Algari Treatise on Mining",
         "nskillup":1,
         "quality":3,
         "reagents":[
            [
               213610,
               2
            ],
            [
               222558,
               1
            ],
            [
               222609,
               2
            ]
         ],
         "schools":1,
         "skill":[
            773
         ],
         "optionalReagents":[
            {
               "id":321,
               "description":"Sable Ink"
            },
            {
               "id":320,
               "description":"Boundless Cipher"
            }
         ]
      },
      {
         "cat":2878,
         "colors":[
            0,
            80,
            90,
            100
         ],
         "creates":[
            222554,
            1,
            1
         ],
         "displayName":"Algari Treatise on Blacksmithing",
         "id":444184,
         "learnedat":80,
         "level":0,
         "name":"Algari Treatise on Blacksmithing",
         "nskillup":1,
         "quality":3,
         "reagents":[
            [
               213611,
               2
            ],
            [
               222558,
               1
            ],
            [
               222609,
               2
            ]
         ],
         "schools":1,
         "skill":[
            773
         ],
         "optionalReagents":[
            {
               "id":321,
               "description":"Sable Ink"
            },
            {
               "id":320,
               "description":"Boundless Cipher"
            }
         ]
      },
      {
         "cat":2878,
         "colors":[
            0,
            80,
            90,
            100
         ],
         "creates":[
            222549,
            1,
            1
         ],
         "displayName":"Algari Treatise on Leatherworking",
         "id":444185,
         "learnedat":80,
         "level":0,
         "name":"Algari Treatise on Leatherworking",
         "nskillup":1,
         "quality":3,
         "reagents":[
            [
               213612,
               2
            ],
            [
               222558,
               1
            ],
            [
               222615,
               2
            ]
         ],
         "schools":1,
         "skill":[
            773
         ],
         "optionalReagents":[
            {
               "id":323,
               "description":"Apricate Ink"
            },
            {
               "id":320,
               "description":"Boundless Cipher"
            }
         ]
      },
      {
         "cat":2878,
         "colors":[
            0,
            80,
            90,
            100
         ],
         "creates":[
            222547,
            1,
            1
         ],
         "displayName":"Algari Treatise on Tailoring",
         "id":444186,
         "learnedat":80,
         "level":0,
         "name":"Algari Treatise on Tailoring",
         "nskillup":1,
         "quality":3,
         "reagents":[
            [
               213613,
               2
            ],
            [
               222558,
               1
            ],
            [
               222615,
               2
            ]
         ],
         "schools":1,
         "skill":[
            773
         ],
         "optionalReagents":[
            {
               "id":323,
               "description":"Apricate Ink"
            },
            {
               "id":320,
               "description":"Boundless Cipher"
            }
         ]
      },
      {
         "cat":2878,
         "colors":[
            0,
            80,
            90,
            100
         ],
         "creates":[
            222546,
            1,
            1
         ],
         "displayName":"Algari Treatise on Alchemy",
         "id":444187,
         "learnedat":80,
         "level":0,
         "name":"Algari Treatise on Alchemy",
         "nskillup":1,
         "quality":3,
         "reagents":[
            [
               213612,
               2
            ],
            [
               222558,
               1
            ],
            [
               222615,
               2
            ]
         ],
         "schools":1,
         "skill":[
            773
         ],
         "optionalReagents":[
            {
               "id":323,
               "description":"Apricate Ink"
            },
            {
               "id":320,
               "description":"Boundless Cipher"
            }
         ]
      },
      {
         "cat":2878,
         "colors":[
            0,
            80,
            90,
            100
         ],
         "creates":[
            222550,
            1,
            1
         ],
         "displayName":"Algari Treatise on Enchanting",
         "id":444188,
         "learnedat":80,
         "level":0,
         "name":"Algari Treatise on Enchanting",
         "nskillup":1,
         "quality":3,
         "reagents":[
            [
               213613,
               2
            ],
            [
               222558,
               1
            ],
            [
               222609,
               2
            ]
         ],
         "schools":1,
         "skill":[
            773
         ],
         "optionalReagents":[
            {
               "id":321,
               "description":"Sable Ink"
            },
            {
               "id":320,
               "description":"Boundless Cipher"
            }
         ]
      },
      {
         "cat":2878,
         "colors":[
            0,
            80,
            90,
            100
         ],
         "creates":[
            222551,
            1,
            1
         ],
         "displayName":"Algari Treatise on Jewelcrafting",
         "id":444189,
         "learnedat":80,
         "level":0,
         "name":"Algari Treatise on Jewelcrafting",
         "nskillup":1,
         "quality":3,
         "reagents":[
            [
               213610,
               2
            ],
            [
               222558,
               1
            ],
            [
               222609,
               2
            ]
         ],
         "schools":1,
         "skill":[
            773
         ],
         "optionalReagents":[
            {
               "id":321,
               "description":"Sable Ink"
            },
            {
               "id":320,
               "description":"Boundless Cipher"
            }
         ]
      },
      {
         "cat":2878,
         "colors":[
            0,
            35,
            40,
            45
         ],
         "creates":[
            222555,
            1,
            1
         ],
         "displayName":"Codified Greenwood",
         "id":444190,
         "learnedat":35,
         "level":0,
         "name":"Codified Greenwood",
         "nskillup":1,
         "quality":3,
         "reagents":[
            [
               226205,
               20
            ],
            [
               210808,
               5
            ],
            [
               222609,
               2
            ]
         ],
         "schools":1,
         "skill":[
            773
         ],
         "source":[
            6
         ],
         "optionalReagents":[
            {
               "id":321,
               "description":"Sable Ink"
            },
            {
               "id":261,
               "description":"Arathor's Spear"
            },
            {
               "id":371,
               "description":"Drafting Supplies"
            },
            {
               "id":346,
               "description":"Artisan's Authenticity"
            }
         ]
      },
      {
         "cat":2878,
         "colors":[
            0,
            30,
            35,
            40
         ],
         "creates":[
            222558,
            1,
            1
         ],
         "displayName":"Boundless Cipher",
         "id":444191,
         "learnedat":30,
         "level":0,
         "name":"Boundless Cipher",
         "nskillup":1,
         "quality":3,
         "reagents":[
            [
               226205,
               20
            ],
            [
               210808,
               5
            ],
            [
               222615,
               2
            ]
         ],
         "schools":1,
         "skill":[
            773
         ],
         "source":[
            6
         ],
         "optionalReagents":[
            {
               "id":323,
               "description":"Apricate Ink"
            },
            {
               "id":261,
               "description":"Arathor's Spear"
            },
            {
               "id":371,
               "description":"Drafting Supplies"
            },
            {
               "id":346,
               "description":"Artisan's Authenticity"
            }
         ]
      },
      {
         "cat":2878,
         "colors":[
            0,
            80,
            90,
            100
         ],
         "creates":[
            226022,
            1,
            1
         ],
         "displayName":"Darkmoon Sigil: Ascension",
         "id":444192,
         "learnedat":80,
         "level":0,
         "name":"Darkmoon Sigil: Ascension",
         "nskillup":1,
         "quality":3,
         "reagents":[
            [
               222680,
               1
            ],
            [
               213611,
               8
            ],
            [
               222558,
               4
            ],
            [
               222609,
               4
            ]
         ],
         "schools":1,
         "skill":[
            773
         ],
         "optionalReagents":[
            {
               "id":321,
               "description":"Sable Ink"
            },
            {
               "id":320,
               "description":"Boundless Cipher"
            },
            {
               "id":371,
               "description":"Drafting Supplies"
            },
            {
               "id":346,
               "description":"Artisan's Authenticity"
            }
         ]
      },
      {
         "cat":2878,
         "colors":[
            0,
            80,
            90,
            100
         ],
         "creates":[
            226025,
            1,
            1
         ],
         "displayName":"Darkmoon Sigil: Radiance",
         "id":444193,
         "learnedat":80,
         "level":0,
         "name":"Darkmoon Sigil: Radiance",
         "nskillup":1,
         "quality":3,
         "reagents":[
            [
               219672,
               1
            ],
            [
               213611,
               8
            ],
            [
               222558,
               4
            ],
            [
               222615,
               4
            ]
         ],
         "schools":1,
         "skill":[
            773
         ],
         "optionalReagents":[
            {
               "id":323,
               "description":"Apricate Ink"
            },
            {
               "id":320,
               "description":"Boundless Cipher"
            },
            {
               "id":371,
               "description":"Drafting Supplies"
            },
            {
               "id":346,
               "description":"Artisan's Authenticity"
            }
         ]
      },
      {
         "cat":2878,
         "colors":[
            0,
            80,
            90,
            100
         ],
         "creates":[
            226028,
            1,
            1
         ],
         "displayName":"Darkmoon Sigil: Symbiosis",
         "id":444194,
         "learnedat":80,
         "level":0,
         "name":"Darkmoon Sigil: Symbiosis",
         "nskillup":1,
         "quality":3,
         "reagents":[
            [
               222653,
               1
            ],
            [
               213611,
               8
            ],
            [
               222558,
               4
            ],
            [
               222609,
               4
            ]
         ],
         "schools":1,
         "skill":[
            773
         ],
         "optionalReagents":[
            {
               "id":321,
               "description":"Sable Ink"
            },
            {
               "id":320,
               "description":"Boundless Cipher"
            },
            {
               "id":371,
               "description":"Drafting Supplies"
            },
            {
               "id":346,
               "description":"Artisan's Authenticity"
            }
         ]
      },
      {
         "cat":2878,
         "colors":[
            0,
            80,
            90,
            100
         ],
         "creates":[
            226031,
            1,
            1
         ],
         "displayName":"Darkmoon Sigil: Vivacity",
         "id":444195,
         "learnedat":80,
         "level":0,
         "name":"Darkmoon Sigil: Vivacity",
         "nskillup":1,
         "quality":3,
         "reagents":[
            [
               222671,
               1
            ],
            [
               213611,
               8
            ],
            [
               222558,
               4
            ],
            [
               222615,
               4
            ]
         ],
         "schools":1,
         "skill":[
            773
         ],
         "optionalReagents":[
            {
               "id":323,
               "description":"Apricate Ink"
            },
            {
               "id":320,
               "description":"Boundless Cipher"
            },
            {
               "id":371,
               "description":"Drafting Supplies"
            },
            {
               "id":346,
               "description":"Artisan's Authenticity"
            }
         ]
      },
      {
         "cat":2878,
         "colors":[
            0,
            30,
            35,
            40
         ],
         "creates":[
            222565,
            1,
            1
         ],
         "displayName":"Inquisitor's Torch",
         "id":444196,
         "learnedat":30,
         "level":0,
         "name":"Inquisitor's Torch",
         "nskillup":1,
         "quality":3,
         "reagents":[
            [
               210808,
               1
            ],
            [
               222558,
               1
            ]
         ],
         "schools":1,
         "skill":[
            773
         ],
         "source":[
            6
         ],
         "optionalReagents":[
            {
               "id":261,
               "description":"Arathor's Spear"
            },
            {
               "id":320,
               "description":"Boundless Cipher"
            },
            {
               "id":340,
               "description":"Add Embellishment"
            },
            {
               "id":283,
               "description":"Customize Secondary Stats"
            },
            {
               "id":342,
               "description":"Empower"
            },
            {
               "id":359,
               "description":"Drafting Supplies"
            },
            {
               "id":346,
               "description":"Artisan's Authenticity"
            }
         ]
      },
      {
         "cat":2878,
         "colors":[
            0,
            100,
            100,
            100
         ],
         "creates":[
            222566,
            1,
            1
         ],
         "displayName":"Vagabond's Torch",
         "id":444197,
         "learnedat":100,
         "level":0,
         "name":"Vagabond's Torch",
         "nskillup":3,
         "quality":4,
         "reagents":[
            [
               213611,
               20
            ],
            [
               222555,
               10
            ],
            [
               222558,
               6
            ]
         ],
         "schools":1,
         "skill":[
            773
         ],
         "optionalReagents":[
            {
               "id":320,
               "description":"Boundless Cipher"
            },
            {
               "id":319,
               "description":"Codified Greenwood"
            },
            {
               "id":256,
               "description":"Spark"
            },
            {
               "id":340,
               "description":"Add Embellishment"
            },
            {
               "id":283,
               "description":"Customize Secondary Stats"
            },
            {
               "id":284,
               "description":"Infuse with Power"
            },
            {
               "id":359,
               "description":"Drafting Supplies"
            },
            {
               "id":346,
               "description":"Artisan's Authenticity"
            },
            {
               "id":384,
               "description":"Augment Beyond"
            }
         ]
      },
      {
         "cat":2878,
         "colors":[
            0,
            100,
            100,
            100
         ],
         "creates":[
            222567,
            1,
            1
         ],
         "displayName":"Vagabond's Careful Crutch",
         "id":444198,
         "learnedat":100,
         "level":0,
         "name":"Vagabond's Careful Crutch",
         "nskillup":3,
         "quality":4,
         "reagents":[
            [
               213611,
               20
            ],
            [
               222555,
               15
            ],
            [
               222558,
               10
            ]
         ],
         "schools":1,
         "skill":[
            773
         ],
         "optionalReagents":[
            {
               "id":320,
               "description":"Boundless Cipher"
            },
            {
               "id":319,
               "description":"Codified Greenwood"
            },
            {
               "id":256,
               "description":"Spark"
            },
            {
               "id":340,
               "description":"Add Embellishment"
            },
            {
               "id":283,
               "description":"Customize Secondary Stats"
            },
            {
               "id":284,
               "description":"Infuse with Power"
            },
            {
               "id":359,
               "description":"Drafting Supplies"
            },
            {
               "id":346,
               "description":"Artisan's Authenticity"
            },
            {
               "id":384,
               "description":"Augment Beyond"
            }
         ]
      },
      {
         "cat":2878,
         "colors":[
            0,
            100,
            100,
            100
         ],
         "creates":[
            222568,
            1,
            1
         ],
         "displayName":"Vagabond's Bounding Baton",
         "id":444199,
         "learnedat":100,
         "level":0,
         "name":"Vagabond's Bounding Baton",
         "nskillup":3,
         "quality":4,
         "reagents":[
            [
               213611,
               20
            ],
            [
               222555,
               15
            ],
            [
               222558,
               10
            ]
         ],
         "schools":1,
         "skill":[
            773
         ],
         "optionalReagents":[
            {
               "id":320,
               "description":"Boundless Cipher"
            },
            {
               "id":319,
               "description":"Codified Greenwood"
            },
            {
               "id":256,
               "description":"Spark"
            },
            {
               "id":340,
               "description":"Add Embellishment"
            },
            {
               "id":283,
               "description":"Customize Secondary Stats"
            },
            {
               "id":284,
               "description":"Infuse with Power"
            },
            {
               "id":359,
               "description":"Drafting Supplies"
            },
            {
               "id":346,
               "description":"Artisan's Authenticity"
            },
            {
               "id":384,
               "description":"Augment Beyond"
            }
         ]
      },
      {
         "cat":2878,
         "colors":[
            0,
            30,
            35,
            40
         ],
         "creates":[
            222569,
            1,
            1
         ],
         "displayName":"Inquisitor's Crutch",
         "id":444200,
         "learnedat":30,
         "level":0,
         "name":"Inquisitor's Crutch",
         "nskillup":1,
         "quality":3,
         "reagents":[
            [
               210808,
               4
            ],
            [
               222558,
               1
            ]
         ],
         "schools":1,
         "skill":[
            773
         ],
         "source":[
            6
         ],
         "optionalReagents":[
            {
               "id":261,
               "description":"Arathor's Spear"
            },
            {
               "id":320,
               "description":"Boundless Cipher"
            },
            {
               "id":340,
               "description":"Add Embellishment"
            },
            {
               "id":283,
               "description":"Customize Secondary Stats"
            },
            {
               "id":342,
               "description":"Empower"
            },
            {
               "id":359,
               "description":"Drafting Supplies"
            },
            {
               "id":346,
               "description":"Artisan's Authenticity"
            }
         ]
      },
      {
         "cat":2878,
         "colors":[
            0,
            30,
            35,
            40
         ],
         "creates":[
            222570,
            1,
            1
         ],
         "displayName":"Inquisitor's Baton",
         "id":444201,
         "learnedat":30,
         "level":0,
         "name":"Inquisitor's Baton",
         "nskillup":1,
         "quality":3,
         "reagents":[
            [
               210808,
               4
            ],
            [
               222558,
               1
            ]
         ],
         "schools":1,
         "skill":[
            773
         ],
         "source":[
            6
         ],
         "optionalReagents":[
            {
               "id":261,
               "description":"Arathor's Spear"
            },
            {
               "id":320,
               "description":"Boundless Cipher"
            },
            {
               "id":340,
               "description":"Add Embellishment"
            },
            {
               "id":283,
               "description":"Customize Secondary Stats"
            },
            {
               "id":342,
               "description":"Empower"
            },
            {
               "id":359,
               "description":"Drafting Supplies"
            },
            {
               "id":346,
               "description":"Artisan's Authenticity"
            }
         ]
      },
      {
         "cat":2878,
         "colors":[
            0,
            80,
            90,
            100
         ],
         "creates":[
            226034,
            1,
            1
         ],
         "displayName":"Vantus Rune: Nerub-ar Palace",
         "id":444203,
         "learnedat":80,
         "level":0,
         "name":"Vantus Rune: Nerub-ar Palace",
         "nskillup":1,
         "quality":3,
         "reagents":[
            [
               213612,
               2
            ],
            [
               222609,
               5
            ],
            [
               222615,
               5
            ]
         ],
         "schools":1,
         "skill":[
            773
         ],
         "source":[
            6
         ],
         "optionalReagents":[
            {
               "id":321,
               "description":"Sable Ink"
            },
            {
               "id":323,
               "description":"Apricate Ink"
            },
            {
               "id":371,
               "description":"Drafting Supplies"
            },
            {
               "id":346,
               "description":"Artisan's Authenticity"
            }
         ]
      },
      {
         "cat":2878,
         "colors":[
            0,
            35,
            40,
            45
         ],
         "creates":[
            222573,
            1,
            1
         ],
         "displayName":"Lightweight Scribe's Quill",
         "id":444204,
         "learnedat":35,
         "level":0,
         "name":"Lightweight Scribe's Quill",
         "nskillup":2,
         "quality":2,
         "reagents":[
            [
               210808,
               8
            ],
            [
               222558,
               1
            ]
         ],
         "schools":1,
         "skill":[
            773
         ],
         "source":[
            6
         ],
         "optionalReagents":[
            {
               "id":261,
               "description":"Arathor's Spear"
            },
            {
               "id":320,
               "description":"Boundless Cipher"
            },
            {
               "id":345,
               "description":"Customize Crafting Stat"
            },
            {
               "id":346,
               "description":"Artisan's Authenticity"
            }
         ]
      },
      {
         "cat":2878,
         "colors":[
            0,
            90,
            100,
            110
         ],
         "creates":[
            222574,
            1,
            1
         ],
         "displayName":"Silver Tongue's Quill",
         "id":444205,
         "learnedat":90,
         "level":0,
         "name":"Silver Tongue's Quill",
         "nskillup":2,
         "quality":3,
         "reagents":[
            [
               210814,
               300
            ],
            [
               213612,
               20
            ],
            [
               222555,
               5
            ],
            [
               222558,
               5
            ]
         ],
         "schools":1,
         "skill":[
            773
         ],
         "optionalReagents":[
            {
               "id":319,
               "description":"Codified Greenwood"
            },
            {
               "id":320,
               "description":"Boundless Cipher"
            },
            {
               "id":345,
               "description":"Customize Crafting Stat"
            },
            {
               "id":346,
               "description":"Artisan's Authenticity"
            }
         ]
      },
      {
         "cat":2878,
         "colors":[
            0,
            35,
            40,
            45
         ],
         "creates":[
            222575,
            1,
            1
         ],
         "displayName":"Hasty Alchemist's Mixing Rod",
         "id":444206,
         "learnedat":35,
         "level":0,
         "name":"Hasty Alchemist's Mixing Rod",
         "nskillup":2,
         "quality":2,
         "reagents":[
            [
               222555,
               2
            ],
            [
               222558,
               1
            ]
         ],
         "schools":1,
         "skill":[
            773
         ],
         "source":[
            6
         ],
         "optionalReagents":[
            {
               "id":319,
               "description":"Codified Greenwood"
            },
            {
               "id":320,
               "description":"Boundless Cipher"
            },
            {
               "id":345,
               "description":"Customize Crafting Stat"
            },
            {
               "id":346,
               "description":"Artisan's Authenticity"
            }
         ]
      },
      {
         "cat":2878,
         "colors":[
            0,
            90,
            100,
            110
         ],
         "creates":[
            222576,
            1,
            1
         ],
         "displayName":"Patient Alchemist's Mixing Rod",
         "id":444207,
         "learnedat":90,
         "level":0,
         "name":"Patient Alchemist's Mixing Rod",
         "nskillup":1,
         "quality":3,
         "reagents":[
            [
               210814,
               300
            ],
            [
               222555,
               20
            ],
            [
               222558,
               15
            ]
         ],
         "schools":1,
         "skill":[
            773
         ],
         "source":[
            2
         ],
         "optionalReagents":[
            {
               "id":320,
               "description":"Boundless Cipher"
            },
            {
               "id":319,
               "description":"Codified Greenwood"
            },
            {
               "id":345,
               "description":"Customize Crafting Stat"
            },
            {
               "id":346,
               "description":"Artisan's Authenticity"
            }
         ]
      },
      {
         "cat":2878,
         "colors":[
            0,
            35,
            40,
            45
         ],
         "creates":[
            222577,
            1,
            1
         ],
         "displayName":"Burnt Rolling Pin",
         "id":444208,
         "learnedat":35,
         "level":0,
         "name":"Burnt Rolling Pin",
         "nskillup":2,
         "quality":2,
         "reagents":[
            [
               222555,
               2
            ],
            [
               222558,
               1
            ]
         ],
         "schools":1,
         "skill":[
            773
         ],
         "source":[
            6
         ],
         "optionalReagents":[
            {
               "id":319,
               "description":"Codified Greenwood"
            },
            {
               "id":320,
               "description":"Boundless Cipher"
            },
            {
               "id":359,
               "description":"Drafting Supplies"
            },
            {
               "id":346,
               "description":"Artisan's Authenticity"
            }
         ]
      },
      {
         "cat":2878,
         "colors":[
            0,
            80,
            90,
            100
         ],
         "creates":[
            222578,
            1,
            1
         ],
         "displayName":"Inscribed Rolling Pin",
         "id":444209,
         "learnedat":80,
         "level":0,
         "name":"Inscribed Rolling Pin",
         "nskillup":2,
         "quality":3,
         "reagents":[
            [
               210814,
               300
            ],
            [
               222555,
               20
            ],
            [
               222558,
               15
            ]
         ],
         "schools":1,
         "skill":[
            773
         ],
         "source":[
            2
         ],
         "optionalReagents":[
            {
               "id":320,
               "description":"Boundless Cipher"
            },
            {
               "id":319,
               "description":"Codified Greenwood"
            },
            {
               "id":359,
               "description":"Drafting Supplies"
            },
            {
               "id":346,
               "description":"Artisan's Authenticity"
            }
         ]
      },
      {
         "cat":2878,
         "colors":[
            0,
            35,
            40,
            45
         ],
         "creates":[
            222579,
            1,
            1
         ],
         "displayName":"Algari Missive of the Aurora",
         "id":444210,
         "learnedat":35,
         "level":0,
         "name":"Algari Missive of the Aurora",
         "nskillup":1,
         "quality":2,
         "reagents":[
            [
               226204,
               2
            ],
            [
               226205,
               5
            ],
            [
               213612,
               5
            ],
            [
               222558,
               1
            ],
            [
               222615,
               1
            ]
         ],
         "schools":1,
         "skill":[
            773
         ],
         "source":[
            6
         ],
         "optionalReagents":[
            {
               "id":323,
               "description":"Apricate Ink"
            },
            {
               "id":320,
               "description":"Boundless Cipher"
            },
            {
               "id":371,
               "description":"Drafting Supplies"
            },
            {
               "id":346,
               "description":"Artisan's Authenticity"
            }
         ]
      },
      {
         "cat":2878,
         "colors":[
            0,
            35,
            40,
            45
         ],
         "creates":[
            222582,
            1,
            1
         ],
         "displayName":"Algari Missive of the Feverflare",
         "id":444211,
         "learnedat":35,
         "level":0,
         "name":"Algari Missive of the Feverflare",
         "nskillup":1,
         "quality":2,
         "reagents":[
            [
               226204,
               2
            ],
            [
               226205,
               5
            ],
            [
               213612,
               5
            ],
            [
               222558,
               1
            ],
            [
               222615,
               1
            ]
         ],
         "schools":1,
         "skill":[
            773
         ],
         "source":[
            6
         ],
         "optionalReagents":[
            {
               "id":323,
               "description":"Apricate Ink"
            },
            {
               "id":320,
               "description":"Boundless Cipher"
            },
            {
               "id":371,
               "description":"Drafting Supplies"
            },
            {
               "id":346,
               "description":"Artisan's Authenticity"
            }
         ]
      },
      {
         "cat":2878,
         "colors":[
            0,
            45,
            50,
            55
         ],
         "creates":[
            222585,
            1,
            1
         ],
         "displayName":"Algari Missive of the Fireflash",
         "id":444212,
         "learnedat":45,
         "level":0,
         "name":"Algari Missive of the Fireflash",
         "nskillup":1,
         "quality":2,
         "reagents":[
            [
               226204,
               2
            ],
            [
               226205,
               5
            ],
            [
               213612,
               5
            ],
            [
               222558,
               1
            ],
            [
               222615,
               1
            ]
         ],
         "schools":1,
         "skill":[
            773
         ],
         "source":[
            6
         ],
         "optionalReagents":[
            {
               "id":323,
               "description":"Apricate Ink"
            },
            {
               "id":320,
               "description":"Boundless Cipher"
            },
            {
               "id":371,
               "description":"Drafting Supplies"
            },
            {
               "id":346,
               "description":"Artisan's Authenticity"
            }
         ]
      },
      {
         "cat":2878,
         "colors":[
            0,
            45,
            50,
            55
         ],
         "creates":[
            222588,
            1,
            1
         ],
         "displayName":"Algari Missive of the Harmonious",
         "id":444213,
         "learnedat":45,
         "level":0,
         "name":"Algari Missive of the Harmonious",
         "nskillup":1,
         "quality":2,
         "reagents":[
            [
               226204,
               2
            ],
            [
               226205,
               5
            ],
            [
               213612,
               5
            ],
            [
               222558,
               1
            ],
            [
               222615,
               1
            ]
         ],
         "schools":1,
         "skill":[
            773
         ],
         "source":[
            6
         ],
         "optionalReagents":[
            {
               "id":323,
               "description":"Apricate Ink"
            },
            {
               "id":320,
               "description":"Boundless Cipher"
            },
            {
               "id":371,
               "description":"Drafting Supplies"
            },
            {
               "id":346,
               "description":"Artisan's Authenticity"
            }
         ]
      },
      {
         "cat":2878,
         "colors":[
            0,
            55,
            60,
            65
         ],
         "creates":[
            222591,
            1,
            1
         ],
         "displayName":"Algari Missive of the Peerless",
         "id":444214,
         "learnedat":55,
         "level":0,
         "name":"Algari Missive of the Peerless",
         "nskillup":1,
         "quality":2,
         "reagents":[
            [
               226204,
               2
            ],
            [
               226205,
               5
            ],
            [
               213612,
               5
            ],
            [
               222558,
               1
            ],
            [
               222615,
               1
            ]
         ],
         "schools":1,
         "skill":[
            773
         ],
         "source":[
            6
         ],
         "optionalReagents":[
            {
               "id":323,
               "description":"Apricate Ink"
            },
            {
               "id":320,
               "description":"Boundless Cipher"
            },
            {
               "id":371,
               "description":"Drafting Supplies"
            },
            {
               "id":346,
               "description":"Artisan's Authenticity"
            }
         ]
      },
      {
         "cat":2878,
         "colors":[
            0,
            55,
            60,
            65
         ],
         "creates":[
            222594,
            1,
            1
         ],
         "displayName":"Algari Missive of the Quickblade",
         "id":444215,
         "learnedat":55,
         "level":0,
         "name":"Algari Missive of the Quickblade",
         "nskillup":1,
         "quality":2,
         "reagents":[
            [
               226204,
               2
            ],
            [
               226205,
               5
            ],
            [
               213612,
               5
            ],
            [
               222558,
               1
            ],
            [
               222615,
               1
            ]
         ],
         "schools":1,
         "skill":[
            773
         ],
         "source":[
            6
         ],
         "optionalReagents":[
            {
               "id":323,
               "description":"Apricate Ink"
            },
            {
               "id":320,
               "description":"Boundless Cipher"
            },
            {
               "id":371,
               "description":"Drafting Supplies"
            },
            {
               "id":346,
               "description":"Artisan's Authenticity"
            }
         ]
      },
      {
         "cat":2878,
         "colors":[
            0,
            80,
            90,
            100
         ],
         "creates":[
            222600,
            1,
            1
         ],
         "displayName":"Contract: Assembly of the Deeps",
         "id":444217,
         "learnedat":80,
         "level":0,
         "name":"Contract: Assembly of the Deeps",
         "nskillup":1,
         "quality":3,
         "reagents":[
            [
               226204,
               1
            ],
            [
               222609,
               25
            ]
         ],
         "schools":1,
         "skill":[
            773
         ],
         "source":[
            5
         ],
         "optionalReagents":[
            {
               "id":321,
               "description":"Sable Ink"
            },
            {
               "id":371,
               "description":"Drafting Supplies"
            },
            {
               "id":346,
               "description":"Artisan's Authenticity"
            }
         ]
      },
      {
         "cat":2878,
         "colors":[
            0,
            80,
            90,
            100
         ],
         "creates":[
            222603,
            1,
            1
         ],
         "displayName":"Contract: Hallowfall Arathi",
         "id":444218,
         "learnedat":80,
         "level":0,
         "name":"Contract: Hallowfall Arathi",
         "nskillup":1,
         "quality":3,
         "reagents":[
            [
               226204,
               1
            ],
            [
               222615,
               25
            ]
         ],
         "schools":1,
         "skill":[
            773
         ],
         "source":[
            5
         ],
         "optionalReagents":[
            {
               "id":323,
               "description":"Apricate Ink"
            },
            {
               "id":371,
               "description":"Drafting Supplies"
            },
            {
               "id":346,
               "description":"Artisan's Authenticity"
            }
         ]
      },
      {
         "cat":2878,
         "colors":[
            0,
            80,
            90,
            100
         ],
         "creates":[
            222606,
            1,
            1
         ],
         "displayName":"Contract: The Severed Threads",
         "id":444219,
         "learnedat":80,
         "level":0,
         "name":"Contract: The Severed Threads",
         "nskillup":1,
         "quality":3,
         "reagents":[
            [
               226204,
               1
            ],
            [
               222609,
               25
            ]
         ],
         "schools":1,
         "skill":[
            773
         ],
         "source":[
            5
         ],
         "optionalReagents":[
            {
               "id":321,
               "description":"Sable Ink"
            },
            {
               "id":371,
               "description":"Drafting Supplies"
            },
            {
               "id":346,
               "description":"Artisan's Authenticity"
            }
         ]
      },
      {
         "cat":2878,
         "colors":[
            0,
            80,
            90,
            100
         ],
         "creates":[
            222597,
            1,
            1
         ],
         "displayName":"Contract: Council of Dornogal",
         "id":444220,
         "learnedat":80,
         "level":0,
         "name":"Contract: Council of Dornogal",
         "nskillup":1,
         "quality":3,
         "reagents":[
            [
               226204,
               1
            ],
            [
               222615,
               25
            ]
         ],
         "schools":1,
         "skill":[
            773
         ],
         "source":[
            5
         ],
         "optionalReagents":[
            {
               "id":323,
               "description":"Apricate Ink"
            },
            {
               "id":371,
               "description":"Drafting Supplies"
            },
            {
               "id":346,
               "description":"Artisan's Authenticity"
            }
         ]
      },
      {
         "cat":2878,
         "colors":[
            0,
            25,
            30,
            35
         ],
         "creates":[
            222609,
            1,
            1
         ],
         "displayName":"Shadow Ink",
         "id":444221,
         "learnedat":25,
         "level":0,
         "name":"Shadow Ink",
         "nskillup":1,
         "quality":3,
         "reagents":[
            [
               226205,
               20
            ],
            [
               224802,
               5
            ],
            [
               224805,
               5
            ]
         ],
         "schools":1,
         "skill":[
            773
         ],
         "source":[
            6
         ],
         "optionalReagents":[
            {
               "id":355,
               "description":"Orbinid Pigment"
            },
            {
               "id":356,
               "description":"Blossom Pigment"
            },
            {
               "id":371,
               "description":"Drafting Supplies"
            },
            {
               "id":346,
               "description":"Artisan's Authenticity"
            }
         ]
      },
      {
         "cat":2878,
         "colors":[
            0,
            20,
            25,
            30
         ],
         "creates":[
            222615,
            1,
            1
         ],
         "displayName":"Apricate Ink",
         "id":444222,
         "learnedat":20,
         "level":0,
         "name":"Apricate Ink",
         "nskillup":1,
         "quality":3,
         "reagents":[
            [
               226205,
               20
            ],
            [
               222612,
               5
            ],
            [
               222618,
               10
            ]
         ],
         "schools":1,
         "skill":[
            773
         ],
         "source":[
            6
         ],
         "optionalReagents":[
            {
               "id":322,
               "description":"Luredrop Pigment"
            },
            {
               "id":324,
               "description":"Apricate Pigment"
            },
            {
               "id":371,
               "description":"Drafting Supplies"
            },
            {
               "id":346,
               "description":"Artisan's Authenticity"
            }
         ]
      },
      {
         "cat":2878,
         "colors":[
            0,
            80,
            90,
            100
         ],
         "creates":[
            222621,
            1,
            1
         ],
         "displayName":"Algari Treatise on Engineering",
         "id":444223,
         "learnedat":80,
         "level":0,
         "name":"Algari Treatise on Engineering",
         "nskillup":1,
         "quality":3,
         "reagents":[
            [
               213611,
               2
            ],
            [
               222558,
               1
            ],
            [
               222609,
               2
            ]
         ],
         "schools":1,
         "skill":[
            773
         ],
         "optionalReagents":[
            {
               "id":321,
               "description":"Sable Ink"
            },
            {
               "id":320,
               "description":"Boundless Cipher"
            }
         ]
      },
      {
         "cat":2878,
         "colors":[
            0,
            30,
            37,
            45
         ],
         "displayName":"Transcribe: Ascension",
         "id":444224,
         "learnedat":30,
         "level":0,
         "name":"Transcribe: Ascension",
         "nskillup":1,
         "reagents":[
            [
               222609,
               1
            ]
         ],
         "schools":1,
         "skill":[
            773
         ],
         "optionalReagents":[
            {
               "id":321,
               "description":"Sable Ink"
            }
         ]
      },
      {
         "cat":2878,
         "colors":[
            0,
            30,
            37,
            45
         ],
         "displayName":"Transcribe: Vivacity",
         "id":444225,
         "learnedat":30,
         "level":0,
         "name":"Transcribe: Vivacity",
         "nskillup":1,
         "reagents":[
            [
               222609,
               1
            ]
         ],
         "schools":1,
         "skill":[
            773
         ],
         "optionalReagents":[
            {
               "id":321,
               "description":"Sable Ink"
            }
         ]
      },
      {
         "cat":2878,
         "colors":[
            0,
            30,
            37,
            45
         ],
         "displayName":"Transcribe: Symbiosis",
         "id":444226,
         "learnedat":30,
         "level":0,
         "name":"Transcribe: Symbiosis",
         "nskillup":1,
         "reagents":[
            [
               222615,
               1
            ]
         ],
         "schools":1,
         "skill":[
            773
         ],
         "optionalReagents":[
            {
               "id":323,
               "description":"Apricate Ink"
            }
         ]
      },
      {
         "cat":2878,
         "colors":[
            0,
            30,
            37,
            45
         ],
         "displayName":"Transcribe: Radiance",
         "id":444227,
         "learnedat":30,
         "level":0,
         "name":"Transcribe: Radiance",
         "nskillup":1,
         "reagents":[
            [
               222615,
               1
            ]
         ],
         "schools":1,
         "skill":[
            773
         ],
         "optionalReagents":[
            {
               "id":323,
               "description":"Apricate Ink"
            }
         ]
      },
      {
         "cat":2878,
         "colors":[
            0,
            40,
            47,
            55
         ],
         "creates":[
            222626,
            1,
            1
         ],
         "displayName":"Algari Missive of Ingenuity",
         "id":444229,
         "learnedat":40,
         "level":0,
         "name":"Algari Missive of Ingenuity",
         "nskillup":1,
         "quality":2,
         "reagents":[
            [
               226204,
               2
            ],
            [
               226205,
               5
            ],
            [
               213613,
               5
            ],
            [
               222558,
               1
            ],
            [
               222609,
               1
            ]
         ],
         "schools":1,
         "skill":[
            773
         ],
         "source":[
            5
         ],
         "optionalReagents":[
            {
               "id":321,
               "description":"Sable Ink"
            },
            {
               "id":320,
               "description":"Boundless Cipher"
            },
            {
               "id":371,
               "description":"Drafting Supplies"
            },
            {
               "id":346,
               "description":"Artisan's Authenticity"
            }
         ]
      },
      {
         "cat":2878,
         "colors":[
            0,
            40,
            47,
            55
         ],
         "creates":[
            222629,
            1,
            1
         ],
         "displayName":"Algari Missive of Resourcefulness",
         "id":444230,
         "learnedat":40,
         "level":0,
         "name":"Algari Missive of Resourcefulness",
         "nskillup":1,
         "quality":2,
         "reagents":[
            [
               226204,
               2
            ],
            [
               226205,
               5
            ],
            [
               213613,
               5
            ],
            [
               222558,
               1
            ],
            [
               222609,
               1
            ]
         ],
         "schools":1,
         "skill":[
            773
         ],
         "source":[
            5
         ],
         "optionalReagents":[
            {
               "id":321,
               "description":"Sable Ink"
            },
            {
               "id":320,
               "description":"Boundless Cipher"
            },
            {
               "id":371,
               "description":"Drafting Supplies"
            },
            {
               "id":346,
               "description":"Artisan's Authenticity"
            }
         ]
      },
      {
         "cat":2878,
         "colors":[
            0,
            40,
            47,
            55
         ],
         "creates":[
            222632,
            1,
            1
         ],
         "displayName":"Algari Missive of Multicraft",
         "id":444231,
         "learnedat":40,
         "level":0,
         "name":"Algari Missive of Multicraft",
         "nskillup":1,
         "quality":2,
         "reagents":[
            [
               226204,
               2
            ],
            [
               226205,
               5
            ],
            [
               213613,
               5
            ],
            [
               222558,
               1
            ],
            [
               222609,
               1
            ]
         ],
         "schools":1,
         "skill":[
            773
         ],
         "source":[
            5
         ],
         "optionalReagents":[
            {
               "id":321,
               "description":"Sable Ink"
            },
            {
               "id":320,
               "description":"Boundless Cipher"
            },
            {
               "id":371,
               "description":"Drafting Supplies"
            },
            {
               "id":346,
               "description":"Artisan's Authenticity"
            }
         ]
      },
      {
         "cat":2878,
         "colors":[
            0,
            40,
            47,
            55
         ],
         "creates":[
            222635,
            1,
            1
         ],
         "displayName":"Algari Missive of Crafting Speed",
         "id":444232,
         "learnedat":40,
         "level":0,
         "name":"Algari Missive of Crafting Speed",
         "nskillup":1,
         "quality":2,
         "reagents":[
            [
               226204,
               2
            ],
            [
               226205,
               5
            ],
            [
               213613,
               5
            ],
            [
               222558,
               1
            ],
            [
               222609,
               1
            ]
         ],
         "schools":1,
         "skill":[
            773
         ],
         "source":[
            5
         ],
         "optionalReagents":[
            {
               "id":321,
               "description":"Sable Ink"
            },
            {
               "id":320,
               "description":"Boundless Cipher"
            },
            {
               "id":371,
               "description":"Drafting Supplies"
            },
            {
               "id":346,
               "description":"Artisan's Authenticity"
            }
         ]
      },
      {
         "cat":2878,
         "colors":[
            0,
            40,
            47,
            55
         ],
         "creates":[
            222638,
            1,
            1
         ],
         "displayName":"Algari Missive of Finesse",
         "id":444233,
         "learnedat":40,
         "level":0,
         "name":"Algari Missive of Finesse",
         "nskillup":1,
         "quality":2,
         "reagents":[
            [
               226204,
               2
            ],
            [
               226205,
               5
            ],
            [
               213613,
               5
            ],
            [
               222558,
               1
            ],
            [
               222609,
               1
            ]
         ],
         "schools":1,
         "skill":[
            773
         ],
         "source":[
            5
         ],
         "optionalReagents":[
            {
               "id":321,
               "description":"Sable Ink"
            },
            {
               "id":320,
               "description":"Boundless Cipher"
            },
            {
               "id":371,
               "description":"Drafting Supplies"
            },
            {
               "id":346,
               "description":"Artisan's Authenticity"
            }
         ]
      },
      {
         "cat":2878,
         "colors":[
            0,
            40,
            47,
            55
         ],
         "creates":[
            222641,
            1,
            1
         ],
         "displayName":"Algari Missive of Perception",
         "id":444234,
         "learnedat":40,
         "level":0,
         "name":"Algari Missive of Perception",
         "nskillup":1,
         "quality":2,
         "reagents":[
            [
               226204,
               2
            ],
            [
               226205,
               5
            ],
            [
               213613,
               5
            ],
            [
               222558,
               1
            ],
            [
               222609,
               1
            ]
         ],
         "schools":1,
         "skill":[
            773
         ],
         "source":[
            5
         ],
         "optionalReagents":[
            {
               "id":321,
               "description":"Sable Ink"
            },
            {
               "id":320,
               "description":"Boundless Cipher"
            },
            {
               "id":371,
               "description":"Drafting Supplies"
            },
            {
               "id":346,
               "description":"Artisan's Authenticity"
            }
         ]
      },
      {
         "cat":2878,
         "colors":[
            0,
            40,
            47,
            55
         ],
         "creates":[
            222644,
            1,
            1
         ],
         "displayName":"Algari Missive of Deftness",
         "id":444235,
         "learnedat":40,
         "level":0,
         "name":"Algari Missive of Deftness",
         "nskillup":1,
         "quality":2,
         "reagents":[
            [
               226204,
               2
            ],
            [
               226205,
               5
            ],
            [
               213613,
               5
            ],
            [
               222558,
               1
            ],
            [
               222609,
               1
            ]
         ],
         "schools":1,
         "skill":[
            773
         ],
         "source":[
            5
         ],
         "optionalReagents":[
            {
               "id":321,
               "description":"Sable Ink"
            },
            {
               "id":320,
               "description":"Boundless Cipher"
            },
            {
               "id":371,
               "description":"Drafting Supplies"
            },
            {
               "id":346,
               "description":"Artisan's Authenticity"
            }
         ]
      },
      {
         "cat":2878,
         "colors":[
            0,
            80,
            90,
            100
         ],
         "creates":[
            222649,
            1,
            1
         ],
         "displayName":"Algari Treatise on Skinning",
         "id":444236,
         "learnedat":80,
         "level":0,
         "name":"Algari Treatise on Skinning",
         "nskillup":1,
         "quality":3,
         "reagents":[
            [
               213612,
               2
            ],
            [
               222558,
               1
            ],
            [
               222615,
               2
            ]
         ],
         "schools":1,
         "skill":[
            773
         ],
         "optionalReagents":[
            {
               "id":323,
               "description":"Apricate Ink"
            },
            {
               "id":320,
               "description":"Boundless Cipher"
            }
         ]
      },
      {
         "cat":2878,
         "colors":[
            0,
            60,
            65,
            70
         ],
         "creates":[
            219931,
            1,
            1
         ],
         "displayName":"Algari Competitor's Medallion",
         "id":444336,
         "learnedat":60,
         "level":0,
         "name":"Algari Competitor's Medallion",
         "nskillup":2,
         "quality":2,
         "reagents":[
            [
               222558,
               2
            ],
            [
               222609,
               3
            ],
            [
               222615,
               3
            ]
         ],
         "schools":1,
         "skill":[
            773
         ],
         "source":[
            2,
            5
         ],
         "optionalReagents":[
            {
               "id":255,
               "description":"Competitor's Heraldry"
            },
            {
               "id":320,
               "description":"Boundless Cipher"
            },
            {
               "id":346,
               "description":"Artisan's Authenticity"
            },
            {
               "id":359,
               "description":"Drafting Supplies"
            },
            {
               "id":321,
               "description":"Sable Ink"
            },
            {
               "id":323,
               "description":"Apricate Ink"
            }
         ]
      },
      {
         "cat":2878,
         "colors":[
            0,
            60,
            65,
            70
         ],
         "creates":[
            219932,
            1,
            1
         ],
         "displayName":"Algari Competitor's Insignia of Alacrity",
         "id":444337,
         "learnedat":60,
         "level":0,
         "name":"Algari Competitor's Insignia of Alacrity",
         "nskillup":2,
         "quality":2,
         "reagents":[
            [
               222558,
               2
            ],
            [
               222609,
               5
            ],
            [
               222615,
               5
            ]
         ],
         "schools":1,
         "skill":[
            773
         ],
         "source":[
            2,
            5
         ],
         "optionalReagents":[
            {
               "id":255,
               "description":"Competitor's Heraldry"
            },
            {
               "id":320,
               "description":"Boundless Cipher"
            },
            {
               "id":346,
               "description":"Artisan's Authenticity"
            },
            {
               "id":359,
               "description":"Drafting Supplies"
            },
            {
               "id":321,
               "description":"Sable Ink"
            },
            {
               "id":323,
               "description":"Apricate Ink"
            }
         ]
      },
      {
         "cat":2878,
         "colors":[
            0,
            60,
            65,
            70
         ],
         "creates":[
            219933,
            1,
            1
         ],
         "displayName":"Algari Competitor's Emblem",
         "id":444338,
         "learnedat":60,
         "level":0,
         "name":"Algari Competitor's Emblem",
         "nskillup":2,
         "quality":2,
         "reagents":[
            [
               222558,
               2
            ],
            [
               222609,
               5
            ],
            [
               222615,
               5
            ]
         ],
         "schools":1,
         "skill":[
            773
         ],
         "source":[
            2,
            5
         ],
         "optionalReagents":[
            {
               "id":255,
               "description":"Competitor's Heraldry"
            },
            {
               "id":320,
               "description":"Boundless Cipher"
            },
            {
               "id":346,
               "description":"Artisan's Authenticity"
            },
            {
               "id":359,
               "description":"Drafting Supplies"
            },
            {
               "id":321,
               "description":"Sable Ink"
            },
            {
               "id":323,
               "description":"Apricate Ink"
            }
         ]
      },
      {
         "cat":2878,
         "colors":[
            0,
            80,
            90,
            100
         ],
         "creates":[
            222548,
            1,
            1
         ],
         "displayName":"Algari Treatise on Inscription",
         "id":447868,
         "learnedat":80,
         "level":0,
         "name":"Algari Treatise on Inscription",
         "nskillup":1,
         "quality":3,
         "reagents":[
            [
               213613,
               2
            ],
            [
               222558,
               1
            ],
            [
               222615,
               2
            ]
         ],
         "schools":1,
         "skill":[
            773
         ],
         "optionalReagents":[
            {
               "id":323,
               "description":"Apricate Ink"
            },
            {
               "id":320,
               "description":"Boundless Cipher"
            }
         ]
      },
      {
         "cat":2878,
         "colors":[
            0,
            60,
            65,
            70
         ],
         "creates":[
            225372,
            1,
            1
         ],
         "displayName":"Algari Competitor's Lamp",
         "id":455006,
         "learnedat":60,
         "level":0,
         "name":"Algari Competitor's Lamp",
         "nskillup":2,
         "quality":2,
         "reagents":[
            [
               222558,
               3
            ],
            [
               222609,
               6
            ]
         ],
         "schools":1,
         "skill":[
            773
         ],
         "source":[
            2,
            5
         ],
         "optionalReagents":[
            {
               "id":255,
               "description":"Competitor's Heraldry"
            },
            {
               "id":340,
               "description":"Add Embellishment"
            },
            {
               "id":283,
               "description":"Customize Secondary Stats"
            },
            {
               "id":346,
               "description":"Artisan's Authenticity"
            },
            {
               "id":359,
               "description":"Drafting Supplies"
            },
            {
               "id":320,
               "description":"Boundless Cipher"
            },
            {
               "id":321,
               "description":"Sable Ink"
            }
         ]
      },
      {
         "cat":2878,
         "colors":[
            0,
            60,
            65,
            70
         ],
         "creates":[
            225368,
            1,
            1
         ],
         "displayName":"Algari Competitor's Pillar",
         "id":455007,
         "learnedat":60,
         "level":0,
         "name":"Algari Competitor's Pillar",
         "nskillup":2,
         "quality":2,
         "reagents":[
            [
               222555,
               4
            ],
            [
               222615,
               6
            ]
         ],
         "schools":1,
         "skill":[
            773
         ],
         "source":[
            2,
            5
         ],
         "optionalReagents":[
            {
               "id":255,
               "description":"Competitor's Heraldry"
            },
            {
               "id":340,
               "description":"Add Embellishment"
            },
            {
               "id":283,
               "description":"Customize Secondary Stats"
            },
            {
               "id":346,
               "description":"Artisan's Authenticity"
            },
            {
               "id":359,
               "description":"Drafting Supplies"
            },
            {
               "id":319,
               "description":"Codified Greenwood"
            },
            {
               "id":323,
               "description":"Apricate Ink"
            }
         ]
      },
      {
         "cat":2878,
         "colors":[
            0,
            60,
            65,
            70
         ],
         "creates":[
            225369,
            1,
            1
         ],
         "displayName":"Algari Competitor's Staff",
         "id":455008,
         "learnedat":60,
         "level":0,
         "name":"Algari Competitor's Staff",
         "nskillup":2,
         "quality":2,
         "reagents":[
            [
               222555,
               4
            ],
            [
               222609,
               6
            ]
         ],
         "schools":1,
         "skill":[
            773
         ],
         "source":[
            2,
            5
         ],
         "optionalReagents":[
            {
               "id":255,
               "description":"Competitor's Heraldry"
            },
            {
               "id":340,
               "description":"Add Embellishment"
            },
            {
               "id":283,
               "description":"Customize Secondary Stats"
            },
            {
               "id":346,
               "description":"Artisan's Authenticity"
            },
            {
               "id":359,
               "description":"Drafting Supplies"
            },
            {
               "id":319,
               "description":"Codified Greenwood"
            },
            {
               "id":321,
               "description":"Sable Ink"
            }
         ]
      },
      {
         "cat":2878,
         "colors":[
            0,
            80,
            90,
            100
         ],
         "creates":[
            232532,
            1,
            1
         ],
         "displayName":"Contract: The Cartels of Undermine",
         "id":471132,
         "learnedat":80,
         "level":0,
         "name":"Contract: The Cartels of Undermine",
         "nskillup":1,
         "quality":3,
         "reagents":[
            [
               226204,
               1
            ],
            [
               222609,
               25
            ]
         ],
         "schools":1,
         "skill":[
            773
         ],
         "source":[
            5
         ],
         "optionalReagents":[
            {
               "id":321,
               "description":"Sable Ink"
            },
            {
               "id":371,
               "description":"Drafting Supplies"
            },
            {
               "id":346,
               "description":"Artisan's Authenticity"
            }
         ]
      },
      {
         "cat":2878,
         "colors":[
            0,
            80,
            90,
            100
         ],
         "creates":[
            232935,
            1,
            1
         ],
         "displayName":"Vantus Rune: Liberation of Undermine",
         "id":472951,
         "learnedat":80,
         "level":0,
         "name":"Vantus Rune: Liberation of Undermine",
         "nskillup":1,
         "quality":3,
         "reagents":[
            [
               213612,
               2
            ],
            [
               222609,
               5
            ],
            [
               222615,
               5
            ]
         ],
         "schools":1,
         "skill":[
            773
         ],
         "source":[
            5
         ],
         "optionalReagents":[
            {
               "id":321,
               "description":"Sable Ink"
            },
            {
               "id":323,
               "description":"Apricate Ink"
            },
            {
               "id":371,
               "description":"Drafting Supplies"
            },
            {
               "id":346,
               "description":"Artisan's Authenticity"
            }
         ]
      },
      {
         "cat":2878,
         "colors":[
            0,
            60,
            67,
            75
         ],
         "creates":[
            234245,
            1,
            1
         ],
         "displayName":"Glyph of the Ashvane Pistol Shot",
         "id":1213517,
         "learnedat":60,
         "level":0,
         "name":"Glyph of the Ashvane Pistol Shot",
         "nskillup":1,
         "quality":1,
         "reagents":[
            [
               226204,
               1
            ],
            [
               222555,
               1
            ],
            [
               222609,
               1
            ],
            [
               222615,
               1
            ]
         ],
         "schools":1,
         "skill":[
            773
         ],
         "source":[
            2,
            21
         ],
         "optionalReagents":[
            {
               "id":323,
               "description":"Apricate Ink"
            },
            {
               "id":321,
               "description":"Sable Ink"
            },
            {
               "id":319,
               "description":"Codified Greenwood"
            }
         ]
      },
      {
         "cat":2878,
         "colors":[
            0,
            60,
            67,
            75
         ],
         "creates":[
            234246,
            1,
            1
         ],
         "displayName":"Glyph of the Admiral's Pistol Shot",
         "id":1213515,
         "learnedat":60,
         "level":0,
         "name":"Glyph of the Admiral's Pistol Shot",
         "nskillup":1,
         "quality":1,
         "reagents":[
            [
               226204,
               1
            ],
            [
               226205,
               3
            ],
            [
               222558,
               1
            ],
            [
               222609,
               2
            ]
         ],
         "schools":1,
         "skill":[
            773
         ],
         "source":[
            2
         ],
         "optionalReagents":[
            {
               "id":321,
               "description":"Sable Ink"
            },
            {
               "id":320,
               "description":"Boundless Cipher"
            }
         ]
      },
      {
         "cat":2878,
         "colors":[
            0,
            60,
            67,
            75
         ],
         "creates":[
            234247,
            1,
            1
         ],
         "displayName":"Glyph of the Gilded Pistol Shot",
         "id":1213514,
         "learnedat":60,
         "level":0,
         "name":"Glyph of the Gilded Pistol Shot",
         "nskillup":1,
         "quality":1,
         "reagents":[
            [
               226204,
               1
            ],
            [
               222558,
               1
            ],
            [
               222615,
               2
            ]
         ],
         "schools":1,
         "skill":[
            773
         ],
         "source":[
            5
         ],
         "optionalReagents":[
            {
               "id":323,
               "description":"Apricate Ink"
            },
            {
               "id":320,
               "description":"Boundless Cipher"
            }
         ]
      },
      {
         "cat":2878,
         "colors":[
            0,
            60,
            67,
            75
         ],
         "creates":[
            234248,
            1,
            1
         ],
         "displayName":"Glyph of the Twilight Pistol Shot",
         "id":1213512,
         "learnedat":60,
         "level":0,
         "name":"Glyph of the Twilight Pistol Shot",
         "nskillup":1,
         "quality":1,
         "reagents":[
            [
               226204,
               1
            ],
            [
               222558,
               1
            ],
            [
               222609,
               2
            ]
         ],
         "schools":1,
         "skill":[
            773
         ],
         "source":[
            5
         ],
         "optionalReagents":[
            {
               "id":321,
               "description":"Sable Ink"
            },
            {
               "id":320,
               "description":"Boundless Cipher"
            }
         ]
      },
      {
         "cat":2878,
         "colors":[
            0,
            60,
            67,
            75
         ],
         "creates":[
            243051,
            1,
            1
         ],
         "displayName":"Glyph of the Strix",
         "id":1234336,
         "learnedat":60,
         "level":0,
         "name":"Glyph of the Strix",
         "nskillup":1,
         "quality":1,
         "reagents":[
            [
               226204,
               1
            ],
            [
               222558,
               1
            ],
            [
               222609,
               1
            ],
            [
               222615,
               1
            ]
         ],
         "schools":1,
         "skill":[
            773
         ],
         "source":[
            5
         ],
         "optionalReagents":[
            {
               "id":323,
               "description":"Apricate Ink"
            },
            {
               "id":321,
               "description":"Sable Ink"
            },
            {
               "id":320,
               "description":"Boundless Cipher"
            }
         ]
      },
      {
         "cat":2878,
         "colors":[
            0,
            80,
            90,
            100
         ],
         "creates":[
            243821,
            1,
            1
         ],
         "displayName":"Contract: The K'aresh Trust",
         "id":1236170,
         "learnedat":80,
         "level":0,
         "name":"Contract: The K'aresh Trust",
         "nskillup":1,
         "quality":3,
         "reagents":[
            [
               226204,
               1
            ],
            [
               222615,
               25
            ]
         ],
         "schools":1,
         "skill":[
            773
         ],
         "source":[
            5
         ],
         "optionalReagents":[
            {
               "id":323,
               "description":"Apricate Ink"
            },
            {
               "id":371,
               "description":"Drafting Supplies"
            },
            {
               "id":346,
               "description":"Artisan's Authenticity"
            }
         ]
      },
      {
         "cat":2878,
         "colors":[
            0,
            80,
            90,
            100
         ],
         "creates":[
            244147,
            1,
            1
         ],
         "displayName":"Vantus Rune: Manaforge Omega",
         "id":1236908,
         "learnedat":80,
         "level":0,
         "name":"Vantus Rune: Manaforge Omega",
         "nskillup":1,
         "quality":3,
         "reagents":[
            [
               213612,
               2
            ],
            [
               222609,
               5
            ],
            [
               222615,
               5
            ]
         ],
         "schools":1,
         "skill":[
            773
         ],
         "source":[
            5
         ],
         "optionalReagents":[
            {
               "id":321,
               "description":"Sable Ink"
            },
            {
               "id":323,
               "description":"Apricate Ink"
            },
            {
               "id":371,
               "description":"Drafting Supplies"
            },
            {
               "id":346,
               "description":"Artisan's Authenticity"
            }
         ]
      },
      {
         "cat":2878,
         "colors":[
            0,
            80,
            90,
            100
         ],
         "creates":[
            246809,
            1,
            1
         ],
         "displayName":"Inspired Writer's Quill",
         "id":1243994,
         "learnedat":80,
         "level":0,
         "name":"Inspired Writer's Quill",
         "nskillup":1,
         "quality":2,
         "reagents":[
            [
               226204,
               1
            ],
            [
               222615,
               25
            ]
         ],
         "schools":1,
         "skill":[
            773
         ],
         "source":[
            5
         ],
         "optionalReagents":[
            {
               "id":323,
               "description":"Apricate Ink"
            },
            {
               "id":371,
               "description":"Drafting Supplies"
            },
            {
               "id":346,
               "description":"Artisan's Authenticity"
            }
         ]
      },
      {
         "cat":2878,
         "colors":[
            0,
            80,
            90,
            100
         ],
         "creates":[
            249700,
            1,
            1
         ],
         "displayName":"Deal: Cartel Zo",
         "id":1249463,
         "learnedat":80,
         "level":0,
         "name":"Deal: Cartel Zo",
         "nskillup":1,
         "quality":3,
         "reagents":[
            [
               226204,
               1
            ],
            [
               249218,
               1
            ],
            [
               222615,
               25
            ]
         ],
         "schools":1,
         "skill":[
            773
         ],
         "source":[
            4
         ],
         "optionalReagents":[
            {
               "id":323,
               "description":"Apricate Ink"
            }
         ]
      },
      {
         "cat":2878,
         "colors":[
            0,
            80,
            90,
            100
         ],
         "creates":[
            249702,
            1,
            1
         ],
         "displayName":"Deal: Cartel Ba",
         "id":1249466,
         "learnedat":80,
         "level":0,
         "name":"Deal: Cartel Ba",
         "nskillup":1,
         "quality":3,
         "reagents":[
            [
               226204,
               1
            ],
            [
               249218,
               1
            ],
            [
               222615,
               25
            ]
         ],
         "schools":1,
         "skill":[
            773
         ],
         "source":[
            4
         ],
         "optionalReagents":[
            {
               "id":323,
               "description":"Apricate Ink"
            }
         ]
      },
      {
         "cat":2878,
         "colors":[
            0,
            80,
            90,
            100
         ],
         "creates":[
            249704,
            1,
            1
         ],
         "displayName":"Deal: Cartel Om",
         "id":1249468,
         "learnedat":80,
         "level":0,
         "name":"Deal: Cartel Om",
         "nskillup":1,
         "quality":3,
         "reagents":[
            [
               226204,
               1
            ],
            [
               249218,
               1
            ],
            [
               222615,
               25
            ]
         ],
         "schools":1,
         "skill":[
            773
         ],
         "source":[
            4
         ],
         "optionalReagents":[
            {
               "id":323,
               "description":"Apricate Ink"
            }
         ]
      }
   ]
}
